wagtail_airtable/__init__.py
wagtail_airtable/apps.py
wagtail_airtable/forms.py
wagtail_airtable/importer.py
wagtail_airtable/mixins.py
wagtail_airtable/serializers.py
wagtail_airtable/utils.py
wagtail_airtable/views.py
wagtail_airtable/wagtail_hooks.py
wagtail_airtable/management/commands/import_airtable.py
wagtail_airtable/management/commands/reset_local_airtable_records.py
wagtail_airtable/migrations/__init__.py
wagtail_airtable/templates/wagtail_airtable/_import_button.html
wagtail_airtable/templates/wagtail_airtable/airtable_import_listing.html
wagtail_airtable/templates/wagtailsnippets/snippets/index.html
wagtail_airtable/templatetags/wagtail_airtable_tags.py
wagtail_airtable-1.0.0.dist-info/LICENSE
wagtail_airtable-1.0.0.dist-info/WHEEL
wagtail_airtable-1.0.0.dist-info/METADATA
wagtail_airtable-1.0.0.dist-info/RECORD
