Metadata-Version: 2.3
Name: wagtail-airtable
Version: 1.0.0
Summary: Sync data between Wagtail and Airtable
Keywords: wagtail,airtable
Author-email: Kalob Taulien <kalob.taulien@torchbox.com>
Maintainer-email: Matthew Westcott <matthew.westcott@torchbox.com>
Requires-Python: >=3.8
Classifier: Environment :: Web Environment
Classifier: Intended Audience :: Developers
Classifier: License :: OSI Approved :: BSD License
Classifier: Operating System :: OS Independent
Classifier: Programming Language :: Python
Classifier: Programming Language :: Python :: 3
Classifier: Programming Language :: Python :: 3.9
Classifier: Programming Language :: Python :: 3.10
Classifier: Programming Language :: Python :: 3.11
Classifier: Programming Language :: Python :: 3.12
Classifier: Programming Language :: Python :: 3.13
Classifier: Framework :: Django
Classifier: Framework :: Django :: 4
Classifier: Framework :: Django :: 5.0
Classifier: Framework :: Django :: 5.1
Classifier: Framework :: Wagtail
Classifier: Framework :: Wagtail :: 5
Classifier: Framework :: Wagtail :: 6
Requires-Dist: Wagtail>=5.2
Requires-Dist: Django>=4.2
Requires-Dist: pyairtable>=2.3,<3
Requires-Dist: djangorestframework>=3.11.0
Requires-Dist: tox>=3.27 ; extra == "testing"
Project-URL: Changelog, https://github.com/wagtail-nest/wagtail-airtable/blob/main/CHANGELOG.md
Project-URL: Documentation, https://github.com/wagtail-nest/wagtail-airtable/blob/main/README.md
Project-URL: Source, https://github.com/wagtail-nest/wagtail-airtable
Provides-Extra: testing
